{
  "_comment": "xgen-frontend main 브랜치(=xgen.x2bee.com) 기준 view 가용성. ok:false 인 view 는 compose.mjs 가 nav 에서 제외함. 소스 갭 분석(stage..main feature-registry diff) 기반으로 수기 작성. 라이브 캡처 후 자동 갱신 가능.",
  "capturedAt": "2026-05-29T00:00:00.000Z",
  "baseUrl": "https://xgen.x2bee.com",
  "views": {
    "main-planning": {
      "ok": false,
      "notFound": true,
      "source": "source-diff",
      "note": "feature-main-planning import 가 main 브랜치 feature-registry.ts 에서 주석 처리됨 (TODO-2026-05-12)"
    },
    "main-teams": {
      "ok": false,
      "notFound": true,
      "source": "source-diff",
      "note": "main-teams import 가 main 브랜치 feature-registry.ts 에서 주석 처리됨 (TODO-2026-05-12)"
    },
    "admin-active-sessions": {
      "ok": false,
      "notFound": true,
      "source": "source-diff",
      "note": "feature-admin-active-sessions import 가 main 브랜치 admin-feature-registry.ts 에 미존재"
    },
    "admin-compute-pool": {
      "ok": false,
      "notFound": true,
      "source": "source-diff",
      "note": "feature-admin-compute-pool import 가 main 브랜치 admin-feature-registry.ts 에 미존재"
    },
    "admin-agentflow-management-info": {
      "ok": false,
      "notFound": true,
      "source": "source-diff",
      "note": "feature-admin-agentflow-management-info import 가 main 브랜치 admin-feature-registry.ts 에 미존재 (info 탭만 빠짐, 챕터 단위 영향은 작음)"
    },
    "upload-history": {
      "ok": false,
      "notFound": true,
      "source": "live-audit",
      "note": "2026-05-29 라이브 전수조사 — Agent 작업실 > 지식관리 사이드바에 '업로드 이력' 메뉴 미노출 (xgen.x2bee.com 에이전트 개발자/시스템관리자/거버넌스 3계정 모두 동일 4개 메뉴: 지식 컬렉션·파일 저장소·DB 연동). 본문 절(15-knowledge.md#upload-history) 은 anchor 로 접근 가능하므로 그대로 두고, 사이드바 매핑 표 행만 인라인 마커로 제거."
    }
  }
}
